pytrends_longitudinal/__init__.py
pytrends_longitudinal-0.1.9.dist-info/LICENSE
pytrends_longitudinal-0.1.9.dist-info/METADATA
pytrends_longitudinal-0.1.9.dist-info/WHEEL
pytrends_longitudinal-0.1.9.dist-info/top_level.txt
pytrends_longitudinal-0.1.9.dist-info/RECORD
