Metadata-Version: 2.1
Name: pytrends-longitudinal
Version: 0.1.9
Summary: Generate long-term longitudinal Google Trends Data
Author: Mohammad Saleh Ahsan Sakir, Taeyong Park
Author-email: ahsansakir506@gmail.com, taeyongp@andrew.cmu.edu
License: MIT
Project-URL: homepage, https://github.com/Mohammad-sakir/pytrends-longitudinal
Keywords: longitudinal-trends longitudinal data python google-trends-api google-trends search-data
Classifier: Programming Language :: Python :: 3
Classifier: Development Status :: 2 - Pre-Alpha
Classifier: Intended Audience :: Developers
Classifier: License :: OSI Approved :: MIT License
Classifier: Operating System :: OS Independent
Requires-Python: >=3.7
License-File: LICENSE
Requires-Dist: ipython
Requires-Dist: pandas
Requires-Dist: python-dateutil
Requires-Dist: pytrends
Requires-Dist: rich
